crate_anon/__init__.py
crate_anon/version.py
crate_anon/anonymise/__init__.py
crate_anon/anonymise/altermethod.py
crate_anon/anonymise/anonregex.py
crate_anon/anonymise/anonymise.py
crate_anon/anonymise/anonymise_cli.py
crate_anon/anonymise/config.py
crate_anon/anonymise/config_singleton.py
crate_anon/anonymise/constants.py
crate_anon/anonymise/dbholder.py
crate_anon/anonymise/dd.py
crate_anon/anonymise/ddr.py
crate_anon/anonymise/eponyms.py
crate_anon/anonymise/fetch_wordlists.py
crate_anon/anonymise/launch_multiprocess_anonymiser.py
crate_anon/anonymise/make_demo_database.py
crate_anon/anonymise/models.py
crate_anon/anonymise/patient.py
crate_anon/anonymise/scrub.py
crate_anon/anonymise/test_anonymisation.py
crate_anon/anonymise/test_extract_text.py
crate_anon/common/__init__.py
crate_anon/common/bugfix_flashtext.py
crate_anon/common/constants.py
crate_anon/common/dockerfunc.py
crate_anon/common/exceptions.py
crate_anon/common/extendedconfigparser.py
crate_anon/common/file_io.py
crate_anon/common/formatting.py
crate_anon/common/memsize.py
crate_anon/common/parallel.py
crate_anon/common/profiling.py
crate_anon/common/regex_helpers.py
crate_anon/common/sql.py
crate_anon/common/stringfunc.py
crate_anon/crateweb/__init__.py
crate_anon/crateweb/manage.py
crate_anon/crateweb/config/__init__.py
crate_anon/crateweb/config/apps.py
crate_anon/crateweb/config/constants.py
crate_anon/crateweb/config/settings.py
crate_anon/crateweb/config/urls.py
crate_anon/crateweb/config/wsgi.py
crate_anon/crateweb/consent/__init__.py
crate_anon/crateweb/consent/celery.py
crate_anon/crateweb/consent/forms.py
crate_anon/crateweb/consent/lookup.py
crate_anon/crateweb/consent/lookup_crs.py
crate_anon/crateweb/consent/lookup_dummy.py
crate_anon/crateweb/consent/lookup_rio.py
crate_anon/crateweb/consent/models.py
crate_anon/crateweb/consent/storage.py
crate_anon/crateweb/consent/tasks.py
crate_anon/crateweb/consent/teamlookup.py
crate_anon/crateweb/consent/teamlookup_dummy.py
crate_anon-0.19.2.dist-info/LICENSE
crate_anon-0.19.2.dist-info/METADATA
crate_anon-0.19.2.dist-info/WHEEL
crate_anon-0.19.2.dist-info/entry_points.txt
crate_anon-0.19.2.dist-info/top_level.txt
crate_anon-0.19.2.dist-info/RECORD
